bip_utils/P2PKH.py
bip_utils/P2SH.py
bip_utils/P2WPKH.py
bip_utils/__init__.py
bip_utils/_version.py
bip_utils/base58.py
bip_utils/base58_ex.py
bip_utils/bech32.py
bip_utils/bech32_ex.py
bip_utils/bip32.py
bip_utils/bip32_ex.py
bip_utils/bip32_key_ser.py
bip_utils/bip32_path.py
bip_utils/bip32_utils.py
bip_utils/bip39.py
bip_utils/bip39_ex.py
bip_utils/bip39_wordslist_en.txt
bip_utils/bip44.py
bip_utils/bip44_base.py
bip_utils/bip44_base_ex.py
bip_utils/bip44_coins.py
bip_utils/bip49.py
bip_utils/bip49_coins.py
bip_utils/bip84.py
bip_utils/bip84_coins.py
bip_utils/bip_coin_base.py
bip_utils/bip_coin_conf.py
bip_utils/bip_coin_conf_helper.py
bip_utils/bip_keys.py
bip_utils/eth_addr.py
bip_utils/key_helper.py
bip_utils/utils.py
bip_utils/wif.py
bip_utils/xrp_addr.py
no_pysha3_bip_utils-1.0.5.1.dist-info/LICENSE
no_pysha3_bip_utils-1.0.5.1.dist-info/METADATA
no_pysha3_bip_utils-1.0.5.1.dist-info/WHEEL
no_pysha3_bip_utils-1.0.5.1.dist-info/top_level.txt
no_pysha3_bip_utils-1.0.5.1.dist-info/RECORD
